LICENSE.md
MANIFEST.in
README.md
requirements.txt
setup.cfg
setup.py
is_content/__init__.py
is_content.egg-info/PKG-INFO
is_content.egg-info/SOURCES.txt
is_content.egg-info/dependency_links.txt
is_content.egg-info/top_level.txt