Metadata-Version: 1.1
Name: is-content
Version: 0.0.1
Summary: is_content
Home-page: UNKNOWN
Author: Sciencelogic
Author-email: UNKNOWN
License: Sciencelogic, Inc.
Platform: UNKNOWN
Classifier: Development Status :: 3 - Alpha
Classifier: Intended Audience :: Developers
Classifier: Programming Language :: Python :: 3
